pgnow/__init__.py
pgnow-0.2.4.dist-info/METADATA
pgnow-0.2.4.dist-info/WHEEL
pgnow-0.2.4.dist-info/top_level.txt
pgnow-0.2.4.dist-info/RECORD
