Metadata-Version: 2.1
Name: pgnow
Version: 0.2.4
Summary: A Tool to Integrate PG8000 into your application
Home-page: https://github.com/TrAsGo/pgnow
Author: Fede Kamelhar
Author-email: fkamelhar@gmail.com
License: UNKNOWN
Platform: UNKNOWN
Classifier: Programming Language :: Python :: 3
Classifier: License :: OSI Approved :: MIT License
Classifier: Operating System :: OS Independent
